dutch_workdays/__init__.py
dutch_workdays/core.py
dutch_workdays/easter.py
dutch_workdays/py.typed
dutch_workdays-0.3.1.dist-info/LICENSE
dutch_workdays-0.3.1.dist-info/METADATA
dutch_workdays-0.3.1.dist-info/WHEEL
dutch_workdays-0.3.1.dist-info/top_level.txt
dutch_workdays-0.3.1.dist-info/RECORD
