Metadata-Version: 2.1
Name: dutch-workdays
Version: 0.3.1
Summary: "A very small library that handles with Dutch calendars and holidays 🇳🇱"
Home-page: https://gitlab.com/new10-public/dutch-workdays/
Author: New10
Author-email: pypi-admin@new10.com
License: UNKNOWN
Platform: UNKNOWN
Classifier: Development Status :: 5 - Production/Stable
Classifier: Programming Language :: Python :: 3
Classifier: Programming Language :: Python :: 3.6
Classifier: License :: OSI Approved :: MIT License
Requires-Python: >=3.6
Requires-Dist: dataclasses ; python_version < "3.7"
Provides-Extra: tests
Requires-Dist: flake8 (==3.7.9) ; extra == 'tests'
Requires-Dist: isort[pyproject] (==4.3.21) ; extra == 'tests'
Requires-Dist: mypy (==0.761) ; extra == 'tests'
Requires-Dist: pytest (==5.3.2) ; extra == 'tests'
Requires-Dist: pytest-cov (==2.8.1) ; extra == 'tests'
Requires-Dist: black (==19.10b0) ; extra == 'tests'
Requires-Dist: pre-commit (==1.21.0) ; extra == 'tests'
Requires-Dist: bump2version (==0.5.11) ; extra == 'tests'
